{
    "birth_Nebuzely-ev_05__113_0": {
        "name": "František Jan",
        "surname": "Šesták",
        "birthplace": "Střemy",
        "birthdate": "1861-10-01",
        "father": "Jiří Šesták",
        "father_place_of_living": "Nebudžely",
        "mother": "Anna Polívková",
        "mother_place_of_living": "Nebudžely",
        "region_id": "eca1f82a-536d-4703-9d64-8c59cea6c6e8",
        "file": "pages/recognition_results/birth_Nebuzely-ev_05__113_pp.xml",
        "record_type": "birth"
    },
    "birth_Nebuzely-ev_05__113_1": {
        "name": "Jiří",
        "surname": "Holub",
        "birthplace": "Vrutice",
        "birthdate": "1866-08-18",
        "father": "Václav Holub",
        "father_place_of_living": "Vrutice",
        "mother": "Alžběta Stránská",
        "mother_place_of_living": "Vrutice",
        "region_id": "2bd43e1b-d2ee-4228-969d-b63856cebeb4",
        "file": "pages/recognition_results/birth_Nebuzely-ev_05__113_pp.xml",
        "record_type": "birth"
    },
    "birth_Nebuzely-ev_05__113_2": {
        "name": "Božena",
        "surname": "Pechářek",
        "birthplace": "Nebudžel",
        "birthdate": "186-12-XX",
        "father": "Jan Pechářek",
        "father_place_of_living": "Nebudžel",
        "mother": "Anna Dorská",
        "mother_place_of_living": "Nebudžel",
        "region_id": "862dc00b-e1c8-45be-b523-f296c75d39d2",
        "file": "pages/recognition_results/birth_Nebuzely-ev_05__113_pp.xml",
        "record_type": "birth"
    }
}