{
    "birth_Nebuzely-ev_05__134_0": {
        "name": "Maria Božena",
        "surname": "Martinovská",
        "birthplace": "Nebudžel",
        "birthdate": "1866-01-19",
        "father": "Antonín Martinovský",
        "father_place_of_living": "Nebudžel",
        "mother": "Anna Slavíková",
        "mother_place_of_living": "Střes",
        "region_id": "a98e8cb2-b451-44a2-aa79-860cb02052e1",
        "file": "pages/recognition_results/birth_Nebuzely-ev_05__134_pp.xml",
        "record_type": "birth"
    },
    "birth_Nebuzely-ev_05__134_1": {
        "name": "Josef",
        "surname": "Pecháček",
        "birthplace": "Velký Oujezd",
        "birthdate": "1860-01-21",
        "father": "Václav Pecháček",
        "father_place_of_living": "Zaháje",
        "mother": "Alžběta Ložková",
        "mother_place_of_living": "Zaháje",
        "region_id": "6a258e00-06ff-40a4-aef8-6f6810b648bf",
        "file": "pages/recognition_results/birth_Nebuzely-ev_05__134_pp.xml",
        "record_type": "birth"
    },
    "birth_Nebuzely-ev_05__134_2": {
        "name": "Anna",
        "surname": "Hrdlička",
        "birthplace": "Hostín",
        "birthdate": "1866-01-01",
        "father": "František Hrdlička",
        "father_place_of_living": "Hostín",
        "mother": "Alžběta Zárubová",
        "mother_place_of_living": "Vtelna",
        "region_id": "c36a26a7-beff-410d-8110-e1556d87a2c9",
        "file": "pages/recognition_results/birth_Nebuzely-ev_05__134_pp.xml",
        "record_type": "birth"
    },
    "birth_Nebuzely-ev_05__134_3": {
        "name": "Maria",
        "surname": "Německá",
        "birthplace": "Řepín",
        "birthdate": "1876-01-15",
        "father": "František Kraus",
        "father_place_of_living": "Řepín",
        "mother": "Anna Pochárková",
        "mother_place_of_living": "Řepín",
        "region_id": "789d03aa-1802-4b09-a9e2-aff84a5bd3a3",
        "file": "pages/recognition_results/birth_Nebuzely-ev_05__134_pp.xml",
        "record_type": "birth"
    }
}